evxpredictor/__init__.py
evxpredictor/finalized_model.h5
evxpredictor/logscaler.gz
evxpredictor/mlbot.py
evxpredictor-0.1.7.dist-info/LICENSE
evxpredictor-0.1.7.dist-info/METADATA
evxpredictor-0.1.7.dist-info/WHEEL
evxpredictor-0.1.7.dist-info/top_level.txt
evxpredictor-0.1.7.dist-info/RECORD
