Metadata-Version: 2.1
Name: evxpredictor
Version: 0.1.7
Summary: A package for predicting buy and sell signals
Home-page: https://nkrtech.com
Download-URL: https://github.com/moinonin/evxpredictor/archive/refs/heads/main.zip
Author: Nicolus Rotich
Author-email: nicholas.rotich@gmail.com
License: MIT
Project-URL: Bug Tracker, https://github.com/pypa/evxpredictor/issues
Platform: any
Classifier: License :: OSI Approved :: MIT License
Requires-Python: >=3.9
License-File: LICENSE
Requires-Dist: setuptools (>=58.1.0)
Requires-Dist: wheel (>=0.37.1)
Requires-Dist: keras (==2.8.0)
Requires-Dist: tensorflow (>=2.8.0)
Requires-Dist: scikit-learn (>=1.0.2)
Requires-Dist: scipy (>=1.8.0)
Requires-Dist: h5py (>=3.6.0)
Requires-Dist: fire
